diskstat/Diskstat.template.ahk
diskstat/FyneApp.toml
diskstat/Icon.png
diskstat/Makefile
diskstat/autostart.py
diskstat/bindings.go
diskstat/disk_test.go
diskstat/disks.go
diskstat/disks.py
diskstat/diskstat-api.exe
diskstat/diskstat.exe
diskstat/entry.py
diskstat/gen.py
diskstat/go.mod
diskstat/go.sum
diskstat/layout.go
diskstat/main.go
diskstat/mapfunc.go
diskstat/model.go
diskstat/program.ico
diskstat/server.go
diskstat/server.py
diskstat-2025.3.18.0.dist-info/METADATA
diskstat-2025.3.18.0.dist-info/WHEEL
diskstat-2025.3.18.0.dist-info/entry_points.txt
diskstat-2025.3.18.0.dist-info/licenses/LICENSE
diskstat-2025.3.18.0.dist-info/RECORD
