Metadata-Version: 2.4
Name: diskstat
Version: 2025.3.18.0
Summary: Visualize your disk free space without Windows Explorer
Project-URL: Repository, https://github.com/soda92/diskstat
License-File: LICENSE
Classifier: Intended Audience :: End Users/Desktop
Classifier: License :: OSI Approved :: GNU General Public License v3 (GPLv3)
Classifier: Operating System :: Microsoft :: Windows
Classifier: Programming Language :: Python :: 3
Classifier: Topic :: System :: Filesystems
Classifier: Topic :: Utilities
Requires-Python: >=3.10
